libpnu/__init__.py
libpnu/main.py
pnu_libpnu-1.3.0.data/data/man/man3/libpnu.3.gz
pnu_libpnu-1.3.0.dist-info/License
pnu_libpnu-1.3.0.dist-info/METADATA
pnu_libpnu-1.3.0.dist-info/WHEEL
pnu_libpnu-1.3.0.dist-info/top_level.txt
pnu_libpnu-1.3.0.dist-info/RECORD
